pysimpliroute/__init__.py
pysimpliroute/simpliroute.py
pysimpliroute-0.1.0.dist-info/METADATA
pysimpliroute-0.1.0.dist-info/RECORD
pysimpliroute-0.1.0.dist-info/WHEEL
pysimpliroute-0.1.0.dist-info/top_level.txt
