Metadata-Version: 2.1
Name: pysimpliroute
Version: 0.1.0
Summary: Wrapper for the SimpliRoute service API
Home-page: https://gitlab.com/dansanti/pysimpliroute
Author: Daniel Santibáñez Polanco
Author-email: dansanti@gmail.com
License: GPLV3+
Platform: UNKNOWN
Classifier: Development Status :: 3 - Alpha
Classifier: License :: OSI Approved :: GNU General Public License v3 or later (GPLv3+)
Classifier: Programming Language :: Python :: 2.7
Classifier: Programming Language :: Python :: 3.6
Classifier: Intended Audience :: Developers
Classifier: Topic :: Software Development :: Libraries :: Python Modules
Classifier: Environment :: Console
Requires-Dist: urllib3
